pydload/__init__.py
pydload/__main__.py
pydload/download.py
pydload-1.0.9.dist-info/LICENSE
pydload-1.0.9.dist-info/METADATA
pydload-1.0.9.dist-info/WHEEL
pydload-1.0.9.dist-info/entry_points.txt
pydload-1.0.9.dist-info/top_level.txt
pydload-1.0.9.dist-info/RECORD
